{
  "title": "Calisthenics for Kids: Fun and Engaging Workout Ideas",
  "date": "2024-10-18T00:00:00.000Z",
  "tags": [
    "calisthenics",
    "fitness for kids",
    "fun workouts",
    "kids exercises"
  ],
  "summary": "Calisthenics for kids is a great way to keep them active and healthy. Discover fun and engaging workout ideas that require no equipment and can be done at home or outside.",
  "images": {
    "cover": "https://images.pexels.com/photos/3094230/pexels-photo-3094230.jpeg?auto=compress&cs=tinysrgb&w=800"
  },
  "body": {
    "raw": "\n# Calisthenics for Kids: Fun and Engaging Workout Ideas\n\nKids need to stay active to grow strong and healthy, but finding the right kind of exercise for them can be challenging. Enter calisthenics: a bodyweight-based exercise routine that is not only effective but also fun and engaging for kids. Calisthenics exercises can be done anywhere, require no equipment, and are ideal for improving kids’ strength, coordination, flexibility, and overall fitness. \n\nIn this blog, we’ll explore some fun workout ideas to introduce calisthenics to kids and keep them excited about staying active!\n\n---\n\n## 1. **Why Calisthenics is Perfect for Kids**\n\nCalisthenics is a versatile and simple form of exercise that uses the body’s natural movements. For kids, it offers numerous benefits:\n\n- **Improves Strength and Flexibility**: Bodyweight exercises help kids build muscle strength and improve flexibility without the risk of heavy weights.\n- **Boosts Coordination and Balance**: Movements like squats, jumps, and planks improve coordination and balance.\n- **Promotes Healthy Habits**: Introducing exercise early in life helps kids develop healthy fitness habits they can carry into adulthood.\n- **Fun and Engaging**: Calisthenics can easily be turned into games, challenges, and fun competitions that keep kids motivated.\n\nLet’s dive into some fun and easy workout ideas that will get kids moving while enjoying their workouts.\n\n---\n\n## 2. **Fun Calisthenics Exercises for Kids**\n\n### 2.1. **Animal Walks**\n\nKids love pretending to be animals, so why not turn that into a fun exercise?\n\n- **Bear Crawl**: Have the kids crawl on their hands and feet, keeping their hips low. It strengthens the arms, legs, and core.\n- **Crab Walk**: Kids sit on the floor with their hands behind them and lift their bodies off the ground. Walking like a crab helps improve arm and leg strength.\n- **Frog Jumps**: Kids squat down low like a frog and jump forward as high as they can. This exercise is perfect for leg strength and cardio.\n\n### 2.2. **Jumping Jacks**\n\nA classic exercise that is easy to learn and perfect for burning off energy. Encourage the kids to do as many jumping jacks as they can in 30 seconds. It gets their heart rate up, improves coordination, and strengthens the whole body.\n\n#### Fun Twist: \nTurn it into a **Jumping Jack Challenge** where kids try to beat their own score each round. They’ll love seeing how many more they can do!\n\n### 2.3. **Squat Challenges**\n\nSquats are great for building leg strength and endurance. Kids can have fun with squats by adding playful elements.\n\n- **Air Squats**: Have them squat down and pretend they are picking up an imaginary ball.\n- **Sumo Squats**: Pretend to be sumo wrestlers! Kids will enjoy the wide-legged stance and the challenge of keeping their balance.\n\n#### Fun Twist: \nAdd a competition where they try to see who can hold the squat position the longest. It’s a fun way to engage kids and keep them motivated.\n\n### 2.4. **Superhero Planks**\n\nMake planks fun by turning them into a superhero challenge!\n\n- **Plank**: Kids lie on their stomachs and lift their bodies on their forearms and toes, holding the position like a strong superhero.\n- **Superman Hold**: While in a plank position, have kids lift one arm and the opposite leg like they are flying through the air.\n\n#### Fun Twist: \nTime their planks and see who can be the strongest superhero for the longest time!\n\n### 2.5. **Mountain Climbers**\n\nMountain climbers are a fantastic way to get kids moving fast and work on their cardio, legs, and core.\n\n- Kids get into a push-up position and alternate bringing their knees to their chest as if they are climbing a mountain.\n\n#### Fun Twist: \nCreate an imaginary mountain adventure and ask them to race to the top as fast as they can!\n\n### 2.6. **Star Jumps**\n\nStar jumps are a more exciting version of a regular jump. Kids squat down and explode into the air, extending their arms and legs out to the sides like a star.\n\n#### Fun Twist: \nTurn it into a game where they pretend to be stars shining in the sky, jumping up to “twinkle” as brightly as they can!\n\n---\n\n## 3. **Creating a Fun Calisthenics Routine for Kids**\n\nA structured routine can help keep kids on track with their fitness goals while making sure they have fun in the process. Here’s a simple calisthenics routine that kids can do at home or outdoors:\n\n### **Warm-Up** (5 Minutes)\nStart with some light exercises to get their bodies warmed up:\n- **Jumping Jacks** (1 minute)\n- **Arm Circles** (1 minute)\n- **High Knees** (1 minute)\n- **Leg Swings** (1 minute)\n- **Wrist Circles** (1 minute)\n\n### **Main Workout** (15-20 Minutes)\n\n| Exercise                | Time/Reps           |\n|-------------------------|---------------------|\n| Bear Crawl               | 30 seconds         |\n| Frog Jumps               | 10 reps            |\n| Jumping Jacks            | 30 seconds         |\n| Air Squats               | 10-15 reps         |\n| Crab Walk                | 30 seconds         |\n| Star Jumps               | 10 reps            |\n| Mountain Climbers        | 30 seconds         |\n| Superman Hold (Plank)    | 15-20 seconds      |\n\n#### Fun Tip: \nMake the workout a circuit! After they complete all exercises, have them rest for 1-2 minutes and repeat the entire circuit again.\n\n---\n\n## 4. **Motivating Kids to Stay Active**\n\n### 4.1. **Turn it Into a Game**\nCreate fun fitness games like **\"Simon Says\"** or obstacle courses where kids need to perform different calisthenics exercises to complete the game.\n\n### 4.2. **Set Achievable Challenges**\nKids love challenges! Set small goals like doing 20 squats in a row or holding a plank for 30 seconds. Celebrate their progress as they improve.\n\n### 4.3. **Workout Together**\nGet involved in the workout! Kids are more likely to stay engaged if their parents or siblings join them in the exercises. It turns fitness into family fun.\n\n### 4.4. **Give Positive Reinforcement**\nAlways encourage kids when they complete their exercises. Positive reinforcement like praise or small rewards can make exercise more enjoyable for them.\n\n---\n\n## 5. **Safety Tips for Kids' Calisthenics Workouts**\n\n- **Always Warm Up**: Ensure that kids warm up before starting their workout to avoid injuries.\n- **Use Proper Form**: Teach them the correct way to perform each exercise to prevent strain.\n- **Stay Hydrated**: Encourage them to drink water before, during, and after the workout.\n- **Rest**: Make sure they take breaks between sets and rest on non-workout days to recover.\n\n---\n\n## Final Thoughts\n\nCalisthenics for kids is a fantastic way to keep them active, healthy, and engaged in fitness from a young age. The key to success is making the exercises fun, interactive, and challenging. By incorporating these creative workout ideas, you’ll help kids develop strength, coordination, and a love for fitness that will benefit them throughout their lives.\n\nSo get ready to jump, crawl, and squat with these kid-friendly calisthenics exercises, and watch them thrive with energy and enthusiasm!\n\n",
    "code": "var Component=(()=>{var u=Object.create;var t=Object.defineProperty;var g=Object.getOwnPropertyDescriptor;var m=Object.getOwnPropertyNames;var p=Object.getPrototypeOf,k=Object.prototype.hasOwnProperty;var f=(i,e)=>()=>(e||i((e={exports:{}}).exports,e),e.exports),b=(i,e)=>{for(var a in e)t(i,a,{get:e[a],enumerable:!0})},o=(i,e,a,r)=>{if(e&&typeof e==\"object\"||typeof e==\"function\")for(let s of m(e))!k.call(i,s)&&s!==a&&t(i,s,{get:()=>e[s],enumerable:!(r=g(e,s))||r.enumerable});return i};var w=(i,e,a)=>(a=i!=null?u(p(i)):{},o(e||!i||!i.__esModule?t(a,\"default\",{value:i,enumerable:!0}):a,i)),y=i=>o(t({},\"__esModule\",{value:!0}),i);var h=f((C,l)=>{l.exports=_jsx_runtime});var N={};b(N,{default:()=>d,frontmatter:()=>v});var n=w(h()),v={title:\"Calisthenics for Kids: Fun and Engaging Workout Ideas\",date:\"2024-10-18\",tags:[\"calisthenics\",\"fitness for kids\",\"fun workouts\",\"kids exercises\"],summary:\"Calisthenics for kids is a great way to keep them active and healthy. Discover fun and engaging workout ideas that require no equipment and can be done at home or outside.\",images:{cover:\"https://images.pexels.com/photos/3094230/pexels-photo-3094230.jpeg?auto=compress&cs=tinysrgb&w=800\"}};function c(i){let e={a:\"a\",h1:\"h1\",h2:\"h2\",h3:\"h3\",h4:\"h4\",hr:\"hr\",li:\"li\",p:\"p\",span:\"span\",strong:\"strong\",table:\"table\",tbody:\"tbody\",td:\"td\",th:\"th\",thead:\"thead\",tr:\"tr\",ul:\"ul\",...i.components};return(0,n.jsxs)(n.Fragment,{children:[(0,n.jsxs)(e.h1,{id:\"calisthenics-for-kids-fun-and-engaging-workout-ideas\",children:[(0,n.jsx)(e.a,{className:\"subheading-anchor\",\"aria-label\":\"Link to section\",href:\"#calisthenics-for-kids-fun-and-engaging-workout-ideas\",children:(0,n.jsx)(e.span,{className:\"icon icon-link\"})}),\"Calisthenics for Kids: Fun and Engaging Workout Ideas\"]}),`\n`,(0,n.jsx)(e.p,{children:\"Kids need to stay active to grow strong and healthy, but finding the right kind of exercise for them can be challenging. Enter calisthenics: a bodyweight-based exercise routine that is not only effective but also fun and engaging for kids. Calisthenics exercises can be done anywhere, require no equipment, and are ideal for improving kids\\u2019 strength, coordination, flexibility, and overall fitness.\"}),`\n`,(0,n.jsx)(e.p,{children:\"In this blog, we\\u2019ll explore some fun workout ideas to introduce calisthenics to kids and keep them excited about staying active!\"}),`\n`,(0,n.jsx)(e.hr,{}),`\n`,(0,n.jsxs)(e.h2,{id:\"1-why-calisthenics-is-perfect-for-kids\",children:[(0,n.jsx)(e.a,{className:\"subheading-anchor\",\"aria-label\":\"Link to section\",href:\"#1-why-calisthenics-is-perfect-for-kids\",children:(0,n.jsx)(e.span,{className:\"icon icon-link\"})}),\"1. \",(0,n.jsx)(e.strong,{children:\"Why Calisthenics is Perfect for Kids\"})]}),`\n`,(0,n.jsx)(e.p,{children:\"Calisthenics is a versatile and simple form of exercise that uses the body\\u2019s natural movements. For kids, it offers numerous benefits:\"}),`\n`,(0,n.jsxs)(e.ul,{children:[`\n`,(0,n.jsxs)(e.li,{children:[(0,n.jsx)(e.strong,{children:\"Improves Strength and Flexibility\"}),\": Bodyweight exercises help kids build muscle strength and improve flexibility without the risk of heavy weights.\"]}),`\n`,(0,n.jsxs)(e.li,{children:[(0,n.jsx)(e.strong,{children:\"Boosts Coordination and Balance\"}),\": Movements like squats, jumps, and planks improve coordination and balance.\"]}),`\n`,(0,n.jsxs)(e.li,{children:[(0,n.jsx)(e.strong,{children:\"Promotes Healthy Habits\"}),\": Introducing exercise early in life helps kids develop healthy fitness habits they can carry into adulthood.\"]}),`\n`,(0,n.jsxs)(e.li,{children:[(0,n.jsx)(e.strong,{children:\"Fun and Engaging\"}),\": Calisthenics can easily be turned into games, challenges, and fun competitions that keep kids motivated.\"]}),`\n`]}),`\n`,(0,n.jsx)(e.p,{children:\"Let\\u2019s dive into some fun and easy workout ideas that will get kids moving while enjoying their workouts.\"}),`\n`,(0,n.jsx)(e.hr,{}),`\n`,(0,n.jsxs)(e.h2,{id:\"2-fun-calisthenics-exercises-for-kids\",children:[(0,n.jsx)(e.a,{className:\"subheading-anchor\",\"aria-label\":\"Link to section\",href:\"#2-fun-calisthenics-exercises-for-kids\",children:(0,n.jsx)(e.span,{className:\"icon icon-link\"})}),\"2. \",(0,n.jsx)(e.strong,{children:\"Fun Calisthenics Exercises for Kids\"})]}),`\n`,(0,n.jsxs)(e.h3,{id:\"21-animal-walks\",children:[(0,n.jsx)(e.a,{className:\"subheading-anchor\",\"aria-label\":\"Link to section\",href:\"#21-animal-walks\",children:(0,n.jsx)(e.span,{className:\"icon icon-link\"})}),\"2.1. \",(0,n.jsx)(e.strong,{children:\"Animal Walks\"})]}),`\n`,(0,n.jsx)(e.p,{children:\"Kids love pretending to be animals, so why not turn that into a fun exercise?\"}),`\n`,(0,n.jsxs)(e.ul,{children:[`\n`,(0,n.jsxs)(e.li,{children:[(0,n.jsx)(e.strong,{children:\"Bear Crawl\"}),\": Have the kids crawl on their hands and feet, keeping their hips low. It strengthens the arms, legs, and core.\"]}),`\n`,(0,n.jsxs)(e.li,{children:[(0,n.jsx)(e.strong,{children:\"Crab Walk\"}),\": Kids sit on the floor with their hands behind them and lift their bodies off the ground. Walking like a crab helps improve arm and leg strength.\"]}),`\n`,(0,n.jsxs)(e.li,{children:[(0,n.jsx)(e.strong,{children:\"Frog Jumps\"}),\": Kids squat down low like a frog and jump forward as high as they can. This exercise is perfect for leg strength and cardio.\"]}),`\n`]}),`\n`,(0,n.jsxs)(e.h3,{id:\"22-jumping-jacks\",children:[(0,n.jsx)(e.a,{className:\"subheading-anchor\",\"aria-label\":\"Link to section\",href:\"#22-jumping-jacks\",children:(0,n.jsx)(e.span,{className:\"icon icon-link\"})}),\"2.2. \",(0,n.jsx)(e.strong,{children:\"Jumping Jacks\"})]}),`\n`,(0,n.jsx)(e.p,{children:\"A classic exercise that is easy to learn and perfect for burning off energy. Encourage the kids to do as many jumping jacks as they can in 30 seconds. It gets their heart rate up, improves coordination, and strengthens the whole body.\"}),`\n`,(0,n.jsxs)(e.h4,{id:\"fun-twist\",children:[(0,n.jsx)(e.a,{className:\"subheading-anchor\",\"aria-label\":\"Link to section\",href:\"#fun-twist\",children:(0,n.jsx)(e.span,{className:\"icon icon-link\"})}),\"Fun Twist:\"]}),`\n`,(0,n.jsxs)(e.p,{children:[\"Turn it into a \",(0,n.jsx)(e.strong,{children:\"Jumping Jack Challenge\"}),\" where kids try to beat their own score each round. They\\u2019ll love seeing how many more they can do!\"]}),`\n`,(0,n.jsxs)(e.h3,{id:\"23-squat-challenges\",children:[(0,n.jsx)(e.a,{className:\"subheading-anchor\",\"aria-label\":\"Link to section\",href:\"#23-squat-challenges\",children:(0,n.jsx)(e.span,{className:\"icon icon-link\"})}),\"2.3. \",(0,n.jsx)(e.strong,{children:\"Squat Challenges\"})]}),`\n`,(0,n.jsx)(e.p,{children:\"Squats are great for building leg strength and endurance. Kids can have fun with squats by adding playful elements.\"}),`\n`,(0,n.jsxs)(e.ul,{children:[`\n`,(0,n.jsxs)(e.li,{children:[(0,n.jsx)(e.strong,{children:\"Air Squats\"}),\": Have them squat down and pretend they are picking up an imaginary ball.\"]}),`\n`,(0,n.jsxs)(e.li,{children:[(0,n.jsx)(e.strong,{children:\"Sumo Squats\"}),\": Pretend to be sumo wrestlers! Kids will enjoy the wide-legged stance and the challenge of keeping their balance.\"]}),`\n`]}),`\n`,(0,n.jsxs)(e.h4,{id:\"fun-twist-1\",children:[(0,n.jsx)(e.a,{className:\"subheading-anchor\",\"aria-label\":\"Link to section\",href:\"#fun-twist-1\",children:(0,n.jsx)(e.span,{className:\"icon icon-link\"})}),\"Fun Twist:\"]}),`\n`,(0,n.jsx)(e.p,{children:\"Add a competition where they try to see who can hold the squat position the longest. It\\u2019s a fun way to engage kids and keep them motivated.\"}),`\n`,(0,n.jsxs)(e.h3,{id:\"24-superhero-planks\",children:[(0,n.jsx)(e.a,{className:\"subheading-anchor\",\"aria-label\":\"Link to section\",href:\"#24-superhero-planks\",children:(0,n.jsx)(e.span,{className:\"icon icon-link\"})}),\"2.4. \",(0,n.jsx)(e.strong,{children:\"Superhero Planks\"})]}),`\n`,(0,n.jsx)(e.p,{children:\"Make planks fun by turning them into a superhero challenge!\"}),`\n`,(0,n.jsxs)(e.ul,{children:[`\n`,(0,n.jsxs)(e.li,{children:[(0,n.jsx)(e.strong,{children:\"Plank\"}),\": Kids lie on their stomachs and lift their bodies on their forearms and toes, holding the position like a strong superhero.\"]}),`\n`,(0,n.jsxs)(e.li,{children:[(0,n.jsx)(e.strong,{children:\"Superman Hold\"}),\": While in a plank position, have kids lift one arm and the opposite leg like they are flying through the air.\"]}),`\n`]}),`\n`,(0,n.jsxs)(e.h4,{id:\"fun-twist-2\",children:[(0,n.jsx)(e.a,{className:\"subheading-anchor\",\"aria-label\":\"Link to section\",href:\"#fun-twist-2\",children:(0,n.jsx)(e.span,{className:\"icon icon-link\"})}),\"Fun Twist:\"]}),`\n`,(0,n.jsx)(e.p,{children:\"Time their planks and see who can be the strongest superhero for the longest time!\"}),`\n`,(0,n.jsxs)(e.h3,{id:\"25-mountain-climbers\",children:[(0,n.jsx)(e.a,{className:\"subheading-anchor\",\"aria-label\":\"Link to section\",href:\"#25-mountain-climbers\",children:(0,n.jsx)(e.span,{className:\"icon icon-link\"})}),\"2.5. \",(0,n.jsx)(e.strong,{children:\"Mountain Climbers\"})]}),`\n`,(0,n.jsx)(e.p,{children:\"Mountain climbers are a fantastic way to get kids moving fast and work on their cardio, legs, and core.\"}),`\n`,(0,n.jsxs)(e.ul,{children:[`\n`,(0,n.jsx)(e.li,{children:\"Kids get into a push-up position and alternate bringing their knees to their chest as if they are climbing a mountain.\"}),`\n`]}),`\n`,(0,n.jsxs)(e.h4,{id:\"fun-twist-3\",children:[(0,n.jsx)(e.a,{className:\"subheading-anchor\",\"aria-label\":\"Link to section\",href:\"#fun-twist-3\",children:(0,n.jsx)(e.span,{className:\"icon icon-link\"})}),\"Fun Twist:\"]}),`\n`,(0,n.jsx)(e.p,{children:\"Create an imaginary mountain adventure and ask them to race to the top as fast as they can!\"}),`\n`,(0,n.jsxs)(e.h3,{id:\"26-star-jumps\",children:[(0,n.jsx)(e.a,{className:\"subheading-anchor\",\"aria-label\":\"Link to section\",href:\"#26-star-jumps\",children:(0,n.jsx)(e.span,{className:\"icon icon-link\"})}),\"2.6. \",(0,n.jsx)(e.strong,{children:\"Star Jumps\"})]}),`\n`,(0,n.jsx)(e.p,{children:\"Star jumps are a more exciting version of a regular jump. Kids squat down and explode into the air, extending their arms and legs out to the sides like a star.\"}),`\n`,(0,n.jsxs)(e.h4,{id:\"fun-twist-4\",children:[(0,n.jsx)(e.a,{className:\"subheading-anchor\",\"aria-label\":\"Link to section\",href:\"#fun-twist-4\",children:(0,n.jsx)(e.span,{className:\"icon icon-link\"})}),\"Fun Twist:\"]}),`\n`,(0,n.jsx)(e.p,{children:\"Turn it into a game where they pretend to be stars shining in the sky, jumping up to \\u201Ctwinkle\\u201D as brightly as they can!\"}),`\n`,(0,n.jsx)(e.hr,{}),`\n`,(0,n.jsxs)(e.h2,{id:\"3-creating-a-fun-calisthenics-routine-for-kids\",children:[(0,n.jsx)(e.a,{className:\"subheading-anchor\",\"aria-label\":\"Link to section\",href:\"#3-creating-a-fun-calisthenics-routine-for-kids\",children:(0,n.jsx)(e.span,{className:\"icon icon-link\"})}),\"3. \",(0,n.jsx)(e.strong,{children:\"Creating a Fun Calisthenics Routine for Kids\"})]}),`\n`,(0,n.jsx)(e.p,{children:\"A structured routine can help keep kids on track with their fitness goals while making sure they have fun in the process. Here\\u2019s a simple calisthenics routine that kids can do at home or outdoors:\"}),`\n`,(0,n.jsxs)(e.h3,{id:\"warm-up-5-minutes\",children:[(0,n.jsx)(e.a,{className:\"subheading-anchor\",\"aria-label\":\"Link to section\",href:\"#warm-up-5-minutes\",children:(0,n.jsx)(e.span,{className:\"icon icon-link\"})}),(0,n.jsx)(e.strong,{children:\"Warm-Up\"}),\" (5 Minutes)\"]}),`\n`,(0,n.jsx)(e.p,{children:\"Start with some light exercises to get their bodies warmed up:\"}),`\n`,(0,n.jsxs)(e.ul,{children:[`\n`,(0,n.jsxs)(e.li,{children:[(0,n.jsx)(e.strong,{children:\"Jumping Jacks\"}),\" (1 minute)\"]}),`\n`,(0,n.jsxs)(e.li,{children:[(0,n.jsx)(e.strong,{children:\"Arm Circles\"}),\" (1 minute)\"]}),`\n`,(0,n.jsxs)(e.li,{children:[(0,n.jsx)(e.strong,{children:\"High Knees\"}),\" (1 minute)\"]}),`\n`,(0,n.jsxs)(e.li,{children:[(0,n.jsx)(e.strong,{children:\"Leg Swings\"}),\" (1 minute)\"]}),`\n`,(0,n.jsxs)(e.li,{children:[(0,n.jsx)(e.strong,{children:\"Wrist Circles\"}),\" (1 minute)\"]}),`\n`]}),`\n`,(0,n.jsxs)(e.h3,{id:\"main-workout-15-20-minutes\",children:[(0,n.jsx)(e.a,{className:\"subheading-anchor\",\"aria-label\":\"Link to section\",href:\"#main-workout-15-20-minutes\",children:(0,n.jsx)(e.span,{className:\"icon icon-link\"})}),(0,n.jsx)(e.strong,{children:\"Main Workout\"}),\" (15-20 Minutes)\"]}),`\n`,(0,n.jsxs)(e.table,{children:[(0,n.jsx)(e.thead,{children:(0,n.jsxs)(e.tr,{children:[(0,n.jsx)(e.th,{children:\"Exercise\"}),(0,n.jsx)(e.th,{children:\"Time/Reps\"})]})}),(0,n.jsxs)(e.tbody,{children:[(0,n.jsxs)(e.tr,{children:[(0,n.jsx)(e.td,{children:\"Bear Crawl\"}),(0,n.jsx)(e.td,{children:\"30 seconds\"})]}),(0,n.jsxs)(e.tr,{children:[(0,n.jsx)(e.td,{children:\"Frog Jumps\"}),(0,n.jsx)(e.td,{children:\"10 reps\"})]}),(0,n.jsxs)(e.tr,{children:[(0,n.jsx)(e.td,{children:\"Jumping Jacks\"}),(0,n.jsx)(e.td,{children:\"30 seconds\"})]}),(0,n.jsxs)(e.tr,{children:[(0,n.jsx)(e.td,{children:\"Air Squats\"}),(0,n.jsx)(e.td,{children:\"10-15 reps\"})]}),(0,n.jsxs)(e.tr,{children:[(0,n.jsx)(e.td,{children:\"Crab Walk\"}),(0,n.jsx)(e.td,{children:\"30 seconds\"})]}),(0,n.jsxs)(e.tr,{children:[(0,n.jsx)(e.td,{children:\"Star Jumps\"}),(0,n.jsx)(e.td,{children:\"10 reps\"})]}),(0,n.jsxs)(e.tr,{children:[(0,n.jsx)(e.td,{children:\"Mountain Climbers\"}),(0,n.jsx)(e.td,{children:\"30 seconds\"})]}),(0,n.jsxs)(e.tr,{children:[(0,n.jsx)(e.td,{children:\"Superman Hold (Plank)\"}),(0,n.jsx)(e.td,{children:\"15-20 seconds\"})]})]})]}),`\n`,(0,n.jsxs)(e.h4,{id:\"fun-tip\",children:[(0,n.jsx)(e.a,{className:\"subheading-anchor\",\"aria-label\":\"Link to section\",href:\"#fun-tip\",children:(0,n.jsx)(e.span,{className:\"icon icon-link\"})}),\"Fun Tip:\"]}),`\n`,(0,n.jsx)(e.p,{children:\"Make the workout a circuit! After they complete all exercises, have them rest for 1-2 minutes and repeat the entire circuit again.\"}),`\n`,(0,n.jsx)(e.hr,{}),`\n`,(0,n.jsxs)(e.h2,{id:\"4-motivating-kids-to-stay-active\",children:[(0,n.jsx)(e.a,{className:\"subheading-anchor\",\"aria-label\":\"Link to section\",href:\"#4-motivating-kids-to-stay-active\",children:(0,n.jsx)(e.span,{className:\"icon icon-link\"})}),\"4. \",(0,n.jsx)(e.strong,{children:\"Motivating Kids to Stay Active\"})]}),`\n`,(0,n.jsxs)(e.h3,{id:\"41-turn-it-into-a-game\",children:[(0,n.jsx)(e.a,{className:\"subheading-anchor\",\"aria-label\":\"Link to section\",href:\"#41-turn-it-into-a-game\",children:(0,n.jsx)(e.span,{className:\"icon icon-link\"})}),\"4.1. \",(0,n.jsx)(e.strong,{children:\"Turn it Into a Game\"})]}),`\n`,(0,n.jsxs)(e.p,{children:[\"Create fun fitness games like \",(0,n.jsx)(e.strong,{children:'\"Simon Says\"'}),\" or obstacle courses where kids need to perform different calisthenics exercises to complete the game.\"]}),`\n`,(0,n.jsxs)(e.h3,{id:\"42-set-achievable-challenges\",children:[(0,n.jsx)(e.a,{className:\"subheading-anchor\",\"aria-label\":\"Link to section\",href:\"#42-set-achievable-challenges\",children:(0,n.jsx)(e.span,{className:\"icon icon-link\"})}),\"4.2. \",(0,n.jsx)(e.strong,{children:\"Set Achievable Challenges\"})]}),`\n`,(0,n.jsx)(e.p,{children:\"Kids love challenges! Set small goals like doing 20 squats in a row or holding a plank for 30 seconds. Celebrate their progress as they improve.\"}),`\n`,(0,n.jsxs)(e.h3,{id:\"43-workout-together\",children:[(0,n.jsx)(e.a,{className:\"subheading-anchor\",\"aria-label\":\"Link to section\",href:\"#43-workout-together\",children:(0,n.jsx)(e.span,{className:\"icon icon-link\"})}),\"4.3. \",(0,n.jsx)(e.strong,{children:\"Workout Together\"})]}),`\n`,(0,n.jsx)(e.p,{children:\"Get involved in the workout! Kids are more likely to stay engaged if their parents or siblings join them in the exercises. It turns fitness into family fun.\"}),`\n`,(0,n.jsxs)(e.h3,{id:\"44-give-positive-reinforcement\",children:[(0,n.jsx)(e.a,{className:\"subheading-anchor\",\"aria-label\":\"Link to section\",href:\"#44-give-positive-reinforcement\",children:(0,n.jsx)(e.span,{className:\"icon icon-link\"})}),\"4.4. \",(0,n.jsx)(e.strong,{children:\"Give Positive Reinforcement\"})]}),`\n`,(0,n.jsx)(e.p,{children:\"Always encourage kids when they complete their exercises. Positive reinforcement like praise or small rewards can make exercise more enjoyable for them.\"}),`\n`,(0,n.jsx)(e.hr,{}),`\n`,(0,n.jsxs)(e.h2,{id:\"5-safety-tips-for-kids-calisthenics-workouts\",children:[(0,n.jsx)(e.a,{className:\"subheading-anchor\",\"aria-label\":\"Link to section\",href:\"#5-safety-tips-for-kids-calisthenics-workouts\",children:(0,n.jsx)(e.span,{className:\"icon icon-link\"})}),\"5. \",(0,n.jsx)(e.strong,{children:\"Safety Tips for Kids' Calisthenics Workouts\"})]}),`\n`,(0,n.jsxs)(e.ul,{children:[`\n`,(0,n.jsxs)(e.li,{children:[(0,n.jsx)(e.strong,{children:\"Always Warm Up\"}),\": Ensure that kids warm up before starting their workout to avoid injuries.\"]}),`\n`,(0,n.jsxs)(e.li,{children:[(0,n.jsx)(e.strong,{children:\"Use Proper Form\"}),\": Teach them the correct way to perform each exercise to prevent strain.\"]}),`\n`,(0,n.jsxs)(e.li,{children:[(0,n.jsx)(e.strong,{children:\"Stay Hydrated\"}),\": Encourage them to drink water before, during, and after the workout.\"]}),`\n`,(0,n.jsxs)(e.li,{children:[(0,n.jsx)(e.strong,{children:\"Rest\"}),\": Make sure they take breaks between sets and rest on non-workout days to recover.\"]}),`\n`]}),`\n`,(0,n.jsx)(e.hr,{}),`\n`,(0,n.jsxs)(e.h2,{id:\"final-thoughts\",children:[(0,n.jsx)(e.a,{className:\"subheading-anchor\",\"aria-label\":\"Link to section\",href:\"#final-thoughts\",children:(0,n.jsx)(e.span,{className:\"icon icon-link\"})}),\"Final Thoughts\"]}),`\n`,(0,n.jsx)(e.p,{children:\"Calisthenics for kids is a fantastic way to keep them active, healthy, and engaged in fitness from a young age. The key to success is making the exercises fun, interactive, and challenging. By incorporating these creative workout ideas, you\\u2019ll help kids develop strength, coordination, and a love for fitness that will benefit them throughout their lives.\"}),`\n`,(0,n.jsx)(e.p,{children:\"So get ready to jump, crawl, and squat with these kid-friendly calisthenics exercises, and watch them thrive with energy and enthusiasm!\"})]})}function d(i={}){let{wrapper:e}=i.components||{};return e?(0,n.jsx)(e,{...i,children:(0,n.jsx)(c,{...i})}):c(i)}return y(N);})();\n;return Component;"
  },
  "_id": "blogs/Calisthenics for Kids Fun and Engaging Workout Ideas.mdx",
  "_raw": {
    "sourceFilePath": "blogs/Calisthenics for Kids Fun and Engaging Workout Ideas.mdx",
    "sourceFileName": "Calisthenics for Kids Fun and Engaging Workout Ideas.mdx",
    "sourceFileDir": "blogs",
    "contentType": "mdx",
    "flattenedPath": "blogs/Calisthenics for Kids Fun and Engaging Workout Ideas"
  },
  "type": "Blog",
  "slug": "calisthenics-for-kids-fun-and-engaging-workout-ideas"
}